spryx_core/__init__.py
spryx_core/constants.py
spryx_core/enums.py
spryx_core/errors.py
spryx_core/id.py
spryx_core/pagination.py
spryx_core/security/__init__.py
spryx_core/security/claims.py
spryx_core/sentinels.py
spryx_core/time.py
spryx_core/types.py
spryx_core-0.1.27.dist-info/LICENSE
spryx_core-0.1.27.dist-info/METADATA
spryx_core-0.1.27.dist-info/WHEEL
spryx_core-0.1.27.dist-info/RECORD
