Metadata-Version: 2.3
Name: spryx-core
Version: 0.1.27
Summary: Core utilities and types for Spryx projects
Author: Pedro Cantidio
Author-email: ppcantidio@gmail.com
Requires-Python: >=3.11
Classifier: Programming Language :: Python :: 3
Classifier: Programming Language :: Python :: 3.11
Classifier: Programming Language :: Python :: 3.12
Classifier: Programming Language :: Python :: 3.13
Requires-Dist: pydantic (>=2.11.3,<3.0.0)
Requires-Dist: python-ulid (>=3.0.0,<4.0.0)
